warpscript/__init__.py
warpscript/warp10_gateway.py
warpscript/warp10_version.py
warpscript/warpscript_magics.py
warpscript/warp10-2.1.0/bin/warp10-2.1.0.jar
warp10_jupyter-1.0.dist-info/METADATA
warp10_jupyter-1.0.dist-info/WHEEL
warp10_jupyter-1.0.dist-info/top_level.txt
warp10_jupyter-1.0.dist-info/RECORD
