Metadata-Version: 2.1
Name: warp10-jupyter
Version: 1.0
Summary: Functions and Jupyter extension for executing WarpScript code
Home-page: http://github.com/senx/warp10-jupyter
Author: Jean-Charles Vialatte
Author-email: jean-charles.vialatte@senx.io
License: Apache 2.0
Platform: UNKNOWN
Requires-Dist: py4j
Requires-Dist: jupyter
Requires-Dist: requests
Requires-Dist: future
